README.rst
setup.cfg
setup.py
jldesmear.egg-info/PKG-INFO
jldesmear.egg-info/SOURCES.txt
jldesmear.egg-info/dependency_links.txt
jldesmear.egg-info/entry_points.txt
jldesmear.egg-info/not-zip-safe
jldesmear.egg-info/requires.txt
jldesmear.egg-info/top_level.txt
src/jldesmear/__init__.py
src/jldesmear/ui.py
src/jldesmear/data/460nm.inp
src/jldesmear/data/460nm.smr
src/jldesmear/data/al2o3.txt
src/jldesmear/data/al2o3_1um.inp
src/jldesmear/data/al2o3_1um.smr
src/jldesmear/data/al2o3_50nm.inp
src/jldesmear/data/al2o3_50nm.smr
src/jldesmear/data/charting.pxp
src/jldesmear/data/model.txt
src/jldesmear/data/model1.dl
src/jldesmear/data/model1.inp
src/jldesmear/data/model1.pin
src/jldesmear/data/model1.smr
src/jldesmear/data/model2.dl
src/jldesmear/data/model2.inp
src/jldesmear/data/model2.smr
src/jldesmear/data/ps120.dsm
src/jldesmear/data/ps120.inp
src/jldesmear/data/ps120.smr
src/jldesmear/data/ps120.txt
src/jldesmear/data/ps460a10.dl
src/jldesmear/data/ps460a10.dsm
src/jldesmear/data/ps460a10.inp
src/jldesmear/data/ps460a10.pxp
src/jldesmear/data/ps460a10.smr
src/jldesmear/data/test1.dsm
src/jldesmear/data/test1.inp
src/jldesmear/data/test1.out
src/jldesmear/data/test1.smr
src/jldesmear/data/test1.xml
src/jldesmear/jl_api/StatsReg.py
src/jldesmear/jl_api/__init__.py
src/jldesmear/jl_api/desmear.py
src/jldesmear/jl_api/extrap_Porod.py
src/jldesmear/jl_api/extrap_constant.py
src/jldesmear/jl_api/extrap_linear.py
src/jldesmear/jl_api/extrap_powerlaw.py
src/jldesmear/jl_api/extrapolation.py
src/jldesmear/jl_api/fileio.py
src/jldesmear/jl_api/fileio_inp.py
src/jldesmear/jl_api/gui.py
src/jldesmear/jl_api/info.py
src/jldesmear/jl_api/smear.py
src/jldesmear/jl_api/test_desmear.py
src/jldesmear/jl_api/test_smear.py
src/jldesmear/jl_api/test_toolbox.py
src/jldesmear/jl_api/textplots.py
src/jldesmear/jl_api/toolbox.py
src/jldesmear/jl_api/traditional.py