Metadata-Version: 1.1
Name: jldesmear
Version: 2015.623.1
Summary: Desmear small-angle scattering data by Jemian and Lake
Home-page: http://jldesmear.readthedocs.org
Author: Pete R Jemian
Author-email: prjemian@gmail.com
License:  (see LICENSE file for details)
Keywords: small-angle,desmearing
Platform: any
Classifier: Development Status :: 4 - Beta
Classifier: Environment :: Console
Classifier: Environment :: Web Environment
Classifier: Intended Audience :: Science/Research
Classifier: License :: Free To Use But Restricted
Classifier: Operating System :: OS Independent
Classifier: Programming Language :: Python
Classifier: Topic :: Scientific/Engineering
Classifier: Topic :: Software Development :: Libraries :: Python Modules
Classifier: Topic :: Utilities
